[
{
	"areaid": 5 ,

	"id": 1 ,

	"name":"紀伊半島大水害記念碑",

	"lat": 33.65652 ,

	"lng": 135.914891 ,

	"era":"平成",

	"address":"那智勝浦町井関",

	"detail":"県道46号線沿い",

	"file":"501.png",

	"exp":"那智勝浦町は、那智川や太田川などの河川沿いと海岸沿いに小規模な平地が形成されています。平成23年8月25日に発生した台風25号で、市野々では9月4日に最大時間雨量123mm、0時から4時までの4時間だけで341㎜の雨量を観測しました。那智川流域の被害の特徴は、支渓流からの土石流が那智川本川に流入したことで、本川沿いの広い範囲で決壊、氾濫、浸水被害が発生したことです。特に那智勝浦町の死者数、建物被害は（全壊・半壊家屋数）は、県全体の半数程度を占めています。平成24年12月20日時点で、那智勝浦町の人的被害は死亡28名、行方不明1名。住宅被害は、全壊103棟、半壊905棟、床上浸水440棟、床下浸水962棟〔文献1より〕。",

	"dist": 20 ,

	"yn":"未",

	"link1":-100 ,

	"link2":-100

},
{
	"areaid": 5 ,

	"id": 2 ,

	"name":"紀伊半島大水害",

	"lat": 33.653604 ,

	"lng": 135.916532 ,

	"era":"平成",

	"address":"那智勝浦町井関",

	"detail":"県道43号線沿い",

	"file":"502.png",

	"exp":"平成23年9月4日午前3時ごろ、「激流を流された女性、フェンスに引っ掛かり一命を留む」と書かれています。9月4日の未明に市野々あたりでも那智川の本川が氾濫したと推測されます。那智川流域の被害の特徴は、支渓流からの土石流が那智川本川に流入したことで、本川沿いの広い範囲で決壊、氾濫が発生し、平成24年12月20日時点で、那智勝浦町の人的被害は死亡28名、行方不明1名。住宅被害は、全壊103棟、半壊905棟、床上浸水440棟、床下浸水962棟〔文献1などより〕。",

	"dist": 20 ,

	"yn":"未",

	"link1":-100 ,

	"link2":-100

},
{
	"areaid": 5 ,

	"id": 3 ,

	"name":"平成13年水害水位標",

	"lat": 33.58813 ,

	"lng": 135.899833 ,

	"era":"平成",

	"address":"那智勝浦町庄",

	"detail":"庄区民会館周辺、県道45号線沿いの三叉路付近の山側",

	"file":"503.png",

	"exp":"日本の南海上を北上していた台風11号は、2001年8月21日午後7時過ぎに紀伊半島最南端の和歌山県串本町付近に上陸。自転車並みのゆっくりとした速度で約半日をかけて紀伊半島を横断し、その間紀伊半島をはじめ四国や近畿、東海地方の各地に大雨を降らせました。特に紀伊半島では21日の日降水量が500～600 mmを記録する大雨となり，各地で浸水被害が相次ぎました。〔文献2より〕",

	"dist": 20 ,

	"yn":"未",

	"link1":-100 ,

	"link2":-100

},
{
	"areaid": 5 ,

	"id": 4 ,

	"name":"開山神社付近の巨石",

	"lat": 33.663427 ,

	"lng": 135.846038 ,

	"era":"江戸",

	"address":"那智勝浦町大野",

	"detail":"開山神社の横",

	"file":"504.png",

	"exp":"1693年9月3日（元禄6年）に、3日より5日まで大雨風で多数の家屋が倒壊し、色川田垣内で村で13人死亡〔文献3などより〕。土石流が発生し、開山神社の横には長さ１０m以上の巨岩が横たわっています。",

	"dist": 20 ,

	"yn":"未",

	"link1":-100 ,

	"link2":-100

},
{
	"areaid": 5 ,

	"id": 5 ,

	"name":"色川の土石流犠牲者供養岩",

	"lat": 33.674566 ,

	"lng": 135.845937 ,

	"era":"江戸",

	"address":"那智勝浦町大野",

	"detail":"大野川に架かる向ノ地橋の周辺",

	"file":"505.png",

	"exp":"1846年8月17日（弘化三年七月七日）、暴風雨で色川村谷の瀬山で、山崩れが発生しました。小規模な天然ダムが形成され、すぐに決壊して、土石流が発生しました。この土石流は大野集落を通り過ぎて2300m流下しました。この土石流によって家屋8戸が押し流され、8名が犠牲となりました。この巨岩もその時に流れ落ちたものです。その後、地域の人々はこの巨岩を供養塔とし、犠牲者を供養してきました。平成28年には、那智勝浦町指定文化財（史跡）に指定されました。〔文献4より〕",

	"dist": 20 ,

	"yn":"未",

	"link1":-100 ,

	"link2":-100

},
{
	"areaid": 5 ,

	"id": 6 ,

	"name":"明治22年水害水位標",

	"lat": 33.729669 ,

	"lng": 135.98465 ,

	"era":"明治",

	"address":"新宮市薬師町",

	"detail":"清閑院の石垣",

	"file":"506.png",

	"exp":"明治22年（1889年）8月に紀伊半島南部を局地的に襲った集中豪雨により十津川村を中心に甚大な被害が発生しました。降雨は3日3晩降り続き、十津川村だけでも死者168人、流失・全半壊家屋610戸、山崩れの箇所1000箇所以上に及び、その土砂は谷を埋め各地で湛水湖が出現しました。この時家や土地を失った600戸、2,500人の被災者は新天地を求め北海道へ集団で移住しました。  〔文献5より〕",

	"dist": 20 ,

	"yn":"未",

	"link1":-100 ,

	"link2":-100

},
{
	"areaid": 5 ,

	"id": 7 ,

	"name":"山津波五十周年供養碑",

	"lat": 33.728877 ,

	"lng": 135.900149 ,

	"era":"昭和",

	"address":"新宮市高田",

	"detail":"近畿大学水産研究所新宮実験場入口前の道(高田川の北岸)を西に道なりに約600m",

	"file":"507.png",

	"exp":"昭和31年(1956)10月29日から30日、紀南地方で700～800mmの集中豪雨があり、河川増水や各所で土砂崩れが発生しました。新宮市西高田・小豆尾地区では、30日17時30分頃、西高田川を隔てた対岸の山が幅30m、長さ数10mの山崩れを起こし、土石流が下にあった民家を襲いました。11名が生き埋めとなり、うち7名が亡くなりました。〔文献6より〕",

	"dist": 20 ,

	"yn":"未",

	"link1":-100 ,

	"link2":-100

},
{
	"areaid": 5 ,

	"id": 8 ,

	"name":"大洪水之迄来ル",

	"lat": 33.803282 ,

	"lng": 135.873874 ,

	"era":"明治",

	"address":"新宮市熊野川町日足",

	"detail":"熊野川小学校周辺",

	"file":"508.png",

	"exp":"明治22年(1889)8月、秋雨前線が日本付近に停滞しているところへ、南海上から台風が接近して、18日から19日にかけて和歌山県から奈良県南部に大雨をもたらしました。この水害による被害は、熊野川流域では死者168人、流失全壊426戸を記録しています。碑はこの水害の際に洪水がここまで来たことを示しています。〔文献6より〕",

	"dist": 20 ,

	"yn":"未",

	"link1":-100 ,

	"link2":-100

},
{
	"areaid": 5 ,

	"id": 9 ,

	"name":"紀伊半島大水害復興祈念碑",

	"lat": 33.798494 ,

	"lng": 135.870194 ,

	"era":"平成",

	"address":"新宮市熊野川町日足",

	"detail":"新宮市さつき公園",

	"file":"509.png",

	"exp":"平成23年9月2日から4日にかけて新宮市を襲った台風12号は、時間雨量130mmを記録、降り始めからの総雨量は1,800㎜を超える大豪雨となりました。市内のいたるところで河川の氾濫や土砂崩れが発生し、死者13名、行方不明者1名、家屋の流失・全半壊326棟、家屋の浸水2,640棟に及ぶ甚大な被害をもたらし、多くの尊い命と大切な財産を奪い去りました。その他、さつき公園について記述されています。",

	"dist": 20 ,

	"yn":"未",

	"link1":-100 ,

	"link2":-100

},
{
	"areaid": 5 ,

	"id": 10 ,

	"name":"紀伊半島大水害慰霊碑",

	"lat": 33.790064 ,

	"lng": 135.896625 ,

	"era":"平成",

	"address":"新宮市熊野川町田?",

	"detail":"道の駅瀞峡街道熊野川周辺",

	"file":"510.png",

	"exp":"平成23年(2011)9月2日から4日、台風12号の影響により長時間続いた雨で熊野川は氾濫し、市内各所で土砂崩れや家屋流失・浸水の被害が発生しました。新宮市では死者・行方不明者14名、住家被害は全壊81棟を含む2,900棟を超え、明治22年(1889)の大水害以来の災害となりました。碑の横にはその時の最高水位8.27mを示したプレートがあります。〔文献6より〕",

	"dist": 20 ,

	"yn":"未",

	"link1":-100 ,

	"link2":-100

},
{
	"areaid": 5 ,

	"id": 11 ,

	"name":"せん水之器と石碑慰霊碑「此土先亡等墓」・石灯籠",

	"lat": 33.861433 ,

	"lng": 135.852224 ,

	"era":"江戸",

	"address":"新宮市熊野川町九重",

	"detail":"九重郵便局の南西、国道311号線から階段がある小道を少し上る",

	"file":"511.png",

	"exp":"災害伝承碑付近に次の説明があります。「この災害慰霊碑は、かつてこの地に住んでいた医師湯川為善が建立したもので、墓石・石碑・手水鉢の三点からなる。漢文で書かれた碑文から察すると、何らかの機縁により自分の住む土地が大きな土砂崩れによりできたものであり、そこにあった建物や住民に大きな被害をもたらしたことに心を痛め、先人の魂を慰めるために文政三年（一八二〇年）、墓石を建立した。ところが、翌年、小さな建物を建てるために整地していたところ、土中から手水鉢を発見する。このことに感動した湯川為善は碑文を刻んだ石碑と手水鉢を墓石の傍らに設置した。（以下省略）」。石碑が建立された1820年以前で比較的近い時期に発生した災害として、〔文献7〕によれば、1788年8月18日（天明7年7月17日）の雷雨洪水があり「夜大雷雨諸方山崩る、那智谷大損し人多死す。那智山粛岩崩壊大滝々壺埋まること十丈余、那智組市野々井関川井関三ヵ村洪水２６人死す。」とあります。この地方でもその時の大雨で被害を受けた可能性があり、この慰霊碑建立との関連も考えられます。",

	"dist": 20 ,

	"yn":"未",

	"link1":-100 ,

	"link2":-100

},
{
	"areaid": 5 ,

	"id": 12 ,

	"name":"台風十二号洪水時最高水位",

	"lat": 33.536027 ,

	"lng": 135.77904 ,

	"era":"平成",

	"address":"古座川町高瀬",

	"detail":"若者広場球技場の駐車場の隅",

	"file":"512.png",

	"exp":"平成23年台風12号による古座川町の住宅被害は、全壊4戸、床上浸水569戸、床下浸水130戸で、9月4日3時時点の避難者は128世帯193人。それ以外の人は各自安全な場所に避難しました。屋根裏部屋や押し入れで水が引くのを待ったとという人も見られ、地区住民や消防団員、庁職員の賢明な救助活動が行われました。〔文献8より〕",

	"dist": 20 ,

	"yn":"未",

	"link1":-100 ,

	"link2":-100

},
{
	"areaid": 5 ,

	"id": 13 ,

	"name":"台風十二号洪水時最高水位",

	"lat": 33.531819 ,

	"lng": 135.815003 ,

	"era":"平成",

	"address":"古座川町高池",

	"detail":"古座川町役場入口付近",

	"file":"513.png",

	"exp":"平成23年台風12号による古座川町の被害は、全壊4戸、床上浸水569戸、床下浸水130戸、町道被害12箇所、橋梁被害2箇所、河川被害3箇所、農道被害1箇所、林道被害15箇所〔文献8より〕",

	"dist": 20 ,

	"yn":"未",

	"link1":-100 ,

	"link2":-100

},
{
	"areaid": 5 ,

	"id": 14 ,

	"name":"紀伊半島大水害警戒碑",

	"lat": 33.91013 ,

	"lng": 135.881339 ,

	"era":"平成",

	"address":"吉野郡十津川村神下",

	"detail":"瀞駐在周辺",

	"file":"514.png",

	"exp":"この碑は、平成23年9月の紀伊半島大水害後、十津川村の村内に建てられたもののひとつです。碑文には、以下のような記述があります。「ここより約10m下の地点まで北山川の水位が上昇した。また、この付近では、電気が約12日間、電話が約4日間使用できなかった。北山川の上流にあたる奈良県上北山村では累積雨量2439ミリメートルを観測した。」（平成26年3月設置）。この台風12号による十津川村の人的被害は、平成24年7月31日現在で、死者7人、行方不明者6人〔文献9より〕。なお、奈良県十津川村は、明治22年の大水害でも甚大な被害を受け、被災住民が多く北海道へ移住しました。",

	"dist": 20 ,

	"yn":"未",

	"link1":-100 ,

	"link2":-100

},
{
	"areaid": 5 ,

	"id": 15 ,

	"name":"紀伊半島大水害最高水位",

	"lat": 33.893284 ,

	"lng": 135.886427 ,

	"era":"平成",

	"address":"新宮市熊野川町下地",

	"detail":"瀞峡めぐり乗船場周辺",

	"file":"515.png",

	"exp":"マリアナ諸島のの西の海上で発生した台風12号に伴う雨量は、新宮市・熊野川町滝川で1828ミリとなりました。熊野川の氾濫で多くの家屋が浸水し、国道168合繊や幹線道路の寸断、山間部での土砂災害などの発生により、新宮市内各地に被害が拡大しました。平成24年1月27日時点で、人的被害は死亡13名（新宮地区内7名、熊野川地区内6名）、行方不明1名（新宮地区内1名）。家屋被害（住家）全壊81棟（新宮地区内28棟、熊野川町地区内53棟）、大規模半壊59棟（新宮地区内9棟、熊野川町地区内50棟）、半壊187棟（新宮地区内64棟、熊野川地区内123棟）、床上浸水1460棟（新宮地区内1399棟、熊野川町地区内61棟）、床下浸水1165棟（新宮地区内1151棟、熊野川町地区内14棟）〔文献10より〕",

	"dist": 20 ,

	"yn":"未",

	"link1":-100 ,

	"link2":-100

},
{
	"areaid": 5 ,

	"id": 16 ,

	"name":"最高最高放水量到達点",

	"lat": 33.907686 ,

	"lng": 135.883514 ,

	"era":"平成",

	"address":"吉野郡十津川村神下",

	"detail":"山彦橋の北岸の主塔付近の石垣に設置されている",

	"file":"516.png",

	"exp":"平成23年9月4日台風12号による最高放水量9,500トン到達点。（行き方：瀞駐在横の階段を降り、瀞ホテルの横を通り過ぎて小道を道なりに歩くと山彦橋に到達します。途中、道幅は人が十分歩ける広さですが、川側は崖になっているので十分注意してください。）",

	"dist": 20 ,

	"yn":"未",

	"link1":-100 ,

	"link2":-100

},
{
	"areaid": 5 ,

	"id": 17 ,

	"name":"和歌山県土砂災害啓発センター",

	"lat": 33.668213 ,

	"lng": 135.903985 ,

	"era":"平成",

	"address":"那智勝浦町市野々3027番6",

	"detail":"国道沿い。大門坂観光案内書付近",

	"file":"517.png",

	"exp":"和歌山県土砂災害啓発センターは、平成23年紀伊半島大水害により甚大な被害を受けた那智勝浦町に、和歌山県が土砂災害に関する研究および啓発の拠点となる施設として設置しました。1階では、パネルや映像を使った土砂災害に関する啓発活動を行っています。2階には、国の大規模土砂災害対策技術センター・大規模土砂災害対策研究機構があり、土砂災害の発生メカニズム等について研究を進めています。",

	"dist": 20 ,

	"yn":"未",

	"link1":-100 ,

	"link2":-100

}
]
